[{"confidence": "0.9236", "file_id": "50", "bbox": "222 54 264 97"}, {"confidence": "0.9189", "file_id": "155", "bbox": "219 149 262 192"}, {"confidence": "0.9124", "file_id": "109", "bbox": "254 96 299 142"}, {"confidence": "0.9053", "file_id": "164", "bbox": "143 125 187 171"}, {"confidence": "0.9042", "file_id": "99", "bbox": "90 15 136 60"}, {"confidence": "0.9028", "file_id": "1", "bbox": "79 61 126 107"}, {"confidence": "0.9021", "file_id": "137", "bbox": "144 137 191 184"}, {"confidence": "0.9016", "file_id": "137", "bbox": "255 72 297 113"}, {"confidence": "0.9015", "file_id": "84", "bbox": "272 130 316 173"}, {"confidence": "0.9014", "file_id": "171", "bbox": "84 23 127 67"}, {"confidence": "0.8997", "file_id": "116", "bbox": "193 135 236 179"}, {"confidence": "0.8996", "file_id": "11", "bbox": "114 60 160 106"}, {"confidence": "0.8992", "file_id": "30", "bbox": "212 123 258 171"}, {"confidence": "0.8989", "file_id": "89", "bbox": "125 27 172 74"}, {"confidence": "0.8955", "file_id": "159", "bbox": "91 96 139 143"}, {"confidence": "0.8953", "file_id": "141", "bbox": "186 130 233 176"}, {"confidence": "0.8953", "file_id": "177", "bbox": "229 22 273 65"}, {"confidence": "0.8935", "file_id": "4", "bbox": "235 63 282 110"}, {"confidence": "0.8914", "file_id": "169", "bbox": "155 128 202 175"}, {"confidence": "0.8890", "file_id": "188", "bbox": "211 38 255 83"}, {"confidence": "0.8874", "file_id": "28", "bbox": "236 159 281 206"}, {"confidence": "0.8856", "file_id": "188", "bbox": "259 112 308 161"}, {"confidence": "0.8854", "file_id": "72", "bbox": "120 123 169 171"}, {"confidence": "0.8853", "file_id": "67", "bbox": "169 138 217 186"}, {"confidence": "0.8843", "file_id": "48", "bbox": "307 81 353 128"}, {"confidence": "0.8830", "file_id": "140", "bbox": "229 117 274 162"}, {"confidence": "0.8821", "file_id": "41", "bbox": "74 11 118 57"}, {"confidence": "0.8809", "file_id": "3", "bbox": "243 1 287 48"}, {"confidence": "0.8794", "file_id": "52", "bbox": "173 138 221 186"}, {"confidence": "0.8791", "file_id": "38", "bbox": "286 62 331 107"}, {"confidence": "0.8790", "file_id": "129", "bbox": "221 128 268 174"}, {"confidence": "0.8786", "file_id": "165", "bbox": "195 21 240 65"}, {"confidence": "0.8758", "file_id": "119", "bbox": "199 125 245 172"}, {"confidence": "0.8754", "file_id": "82", "bbox": "206 92 253 140"}, {"confidence": "0.8738", "file_id": "158", "bbox": "186 80 231 129"}, {"confidence": "0.8729", "file_id": "106", "bbox": "270 130 316 176"}, {"confidence": "0.8727", "file_id": "91", "bbox": "9 78 57 120"}, {"confidence": "0.8726", "file_id": "23", "bbox": "30 12 76 55"}, {"confidence": "0.8694", "file_id": "179", "bbox": "132 59 179 105"}, {"confidence": "0.8679", "file_id": "193", "bbox": "214 53 258 98"}, {"confidence": "0.8678", "file_id": "77", "bbox": "44 41 92 89"}, {"confidence": "0.8661", "file_id": "28", "bbox": "280 41 321 82"}, {"confidence": "0.8657", "file_id": "57", "bbox": "204 90 251 137"}, {"confidence": "0.8651", "file_id": "163", "bbox": "258 52 307 100"}, {"confidence": "0.8634", "file_id": "130", "bbox": "79 66 127 112"}, {"confidence": "0.8630", "file_id": "82", "bbox": "78 41 127 88"}, {"confidence": "0.8622", "file_id": "147", "bbox": "208 98 258 147"}, {"confidence": "0.8600", "file_id": "188", "bbox": "149 124 195 170"}, {"confidence": "0.8581", "file_id": "60", "bbox": "144 52 192 99"}, {"confidence": "0.8563", "file_id": "112", "bbox": "186 118 231 163"}, {"confidence": "0.8538", "file_id": "105", "bbox": "161 98 208 145"}, {"confidence": "0.8527", "file_id": "40", "bbox": "253 50 300 97"}, {"confidence": "0.8517", "file_id": "39", "bbox": "207 143 256 192"}, {"confidence": "0.8512", "file_id": "110", "bbox": "244 29 293 76"}, {"confidence": "0.8499", "file_id": "98", "bbox": "104 51 154 101"}, {"confidence": "0.8496", "file_id": "74", "bbox": "212 155 260 203"}, {"confidence": "0.8495", "file_id": "57", "bbox": "45 74 92 119"}, {"confidence": "0.8491", "file_id": "10", "bbox": "189 165 232 209"}, {"confidence": "0.8486", "file_id": "2", "bbox": "85 93 131 141"}, {"confidence": "0.8479", "file_id": "166", "bbox": "271 119 314 164"}, {"confidence": "0.8468", "file_id": "146", "bbox": "130 98 178 145"}, {"confidence": "0.8464", "file_id": "119", "bbox": "141 12 191 62"}, {"confidence": "0.8434", "file_id": "111", "bbox": "301 25 349 74"}, {"confidence": "0.8420", "file_id": "149", "bbox": "160 131 211 180"}, {"confidence": "0.8412", "file_id": "94", "bbox": "181 60 227 107"}, {"confidence": "0.8380", "file_id": "152", "bbox": "201 119 243 162"}, {"confidence": "0.8369", "file_id": "86", "bbox": "168 100 216 149"}, {"confidence": "0.8349", "file_id": "61", "bbox": "140 171 193 219"}, {"confidence": "0.8341", "file_id": "12", "bbox": "175 52 222 99"}, {"confidence": "0.8330", "file_id": "111", "bbox": "128 119 175 165"}, {"confidence": "0.8328", "file_id": "148", "bbox": "240 58 290 109"}, {"confidence": "0.8318", "file_id": "34", "bbox": "127 96 176 144"}, {"confidence": "0.8295", "file_id": "69", "bbox": "185 26 234 74"}, {"confidence": "0.8294", "file_id": "101", "bbox": "187 73 236 119"}, {"confidence": "0.8292", "file_id": "15", "bbox": "106 109 157 159"}, {"confidence": "0.8280", "file_id": "34", "bbox": "195 57 245 104"}, {"confidence": "0.8277", "file_id": "163", "bbox": "83 89 130 137"}, {"confidence": "0.8257", "file_id": "167", "bbox": "309 96 355 143"}, {"confidence": "0.8255", "file_id": "31", "bbox": "216 115 260 159"}, {"confidence": "0.8219", "file_id": "26", "bbox": "154 101 201 149"}, {"confidence": "0.8202", "file_id": "26", "bbox": "237 129 287 179"}, {"confidence": "0.8179", "file_id": "122", "bbox": "281 42 323 81"}, {"confidence": "0.8176", "file_id": "132", "bbox": "181 78 228 125"}, {"confidence": "0.8143", "file_id": "95", "bbox": "165 58 213 105"}, {"confidence": "0.8139", "file_id": "17", "bbox": "136 127 189 180"}, {"confidence": "0.8132", "file_id": "120", "bbox": "27 114 71 157"}, {"confidence": "0.8119", "file_id": "72", "bbox": "92 41 139 89"}, {"confidence": "0.8081", "file_id": "167", "bbox": "122 142 166 190"}, {"confidence": "0.8074", "file_id": "148", "bbox": "297 100 344 146"}, {"confidence": "0.8068", "file_id": "115", "bbox": "188 157 234 208"}, {"confidence": "0.8034", "file_id": "56", "bbox": "252 114 304 166"}, {"confidence": "0.8022", "file_id": "181", "bbox": "281 25 330 74"}, {"confidence": "0.8017", "file_id": "31", "bbox": "268 120 312 164"}, {"confidence": "0.8004", "file_id": "73", "bbox": "144 93 195 141"}, {"confidence": "0.7988", "file_id": "144", "bbox": "184 40 227 82"}, {"confidence": "0.7980", "file_id": "55", "bbox": "195 161 240 210"}, {"confidence": "0.7943", "file_id": "23", "bbox": "335 67 383 114"}, {"confidence": "0.7917", "file_id": "6", "bbox": "137 134 189 182"}, {"confidence": "0.7917", "file_id": "29", "bbox": "155 62 205 111"}, {"confidence": "0.7903", "file_id": "134", "bbox": "258 58 305 105"}, {"confidence": "0.7796", "file_id": "10", "bbox": "68 117 111 163"}, {"confidence": "0.7771", "file_id": "194", "bbox": "106 130 150 179"}, {"confidence": "0.7765", "file_id": "3", "bbox": "137 74 179 114"}, {"confidence": "0.7737", "file_id": "13", "bbox": "269 114 321 164"}, {"confidence": "0.7727", "file_id": "108", "bbox": "105 21 152 67"}, {"confidence": "0.7702", "file_id": "133", "bbox": "187 72 236 123"}, {"confidence": "0.7595", "file_id": "97", "bbox": "150 40 198 89"}, {"confidence": "0.7568", "file_id": "154", "bbox": "112 3 163 56"}, {"confidence": "0.7547", "file_id": "1", "bbox": "243 153 290 201"}, {"confidence": "0.7485", "file_id": "14", "bbox": "189 165 233 212"}, {"confidence": "0.7462", "file_id": "45", "bbox": "233 176 280 220"}, {"confidence": "0.7462", "file_id": "49", "bbox": "332 18 382 67"}, {"confidence": "0.7445", "file_id": "39", "bbox": "71 113 117 159"}, {"confidence": "0.7445", "file_id": "134", "bbox": "188 130 239 182"}, {"confidence": "0.7440", "file_id": "150", "bbox": "24 53 68 98"}, {"confidence": "0.7409", "file_id": "79", "bbox": "168 41 211 82"}, {"confidence": "0.7399", "file_id": "114", "bbox": "225 174 277 225"}, {"confidence": "0.7384", "file_id": "103", "bbox": "48 75 101 125"}, {"confidence": "0.7366", "file_id": "93", "bbox": "138 23 186 69"}, {"confidence": "0.7337", "file_id": "59", "bbox": "214 11 261 59"}, {"confidence": "0.7319", "file_id": "39", "bbox": "179 80 226 134"}, {"confidence": "0.7311", "file_id": "98", "bbox": "152 79 202 131"}, {"confidence": "0.7306", "file_id": "135", "bbox": "250 134 299 180"}, {"confidence": "0.7190", "file_id": "131", "bbox": "0 0 415 415"}, {"confidence": "0.7140", "file_id": "180", "bbox": "311 134 354 173"}, {"confidence": "0.7082", "file_id": "44", "bbox": "165 125 214 170"}, {"confidence": "0.7055", "file_id": "33", "bbox": "255 136 304 185"}, {"confidence": "0.7040", "file_id": "67", "bbox": "53 79 99 125"}, {"confidence": "0.6897", "file_id": "148", "bbox": "290 43 344 89"}, {"confidence": "0.6775", "file_id": "48", "bbox": "88 61 138 111"}, {"confidence": "0.6762", "file_id": "14", "bbox": "0 0 415 415"}, {"confidence": "0.6595", "file_id": "116", "bbox": "63 116 105 160"}, {"confidence": "0.6582", "file_id": "170", "bbox": "204 7 253 61"}, {"confidence": "0.6518", "file_id": "116", "bbox": "264 93 306 149"}, {"confidence": "0.6513", "file_id": "190", "bbox": "130 123 178 172"}, {"confidence": "0.6450", "file_id": "172", "bbox": "320 91 367 142"}, {"confidence": "0.6418", "file_id": "176", "bbox": "0 0 415 415"}, {"confidence": "0.6417", "file_id": "82", "bbox": "47 98 92 146"}, {"confidence": "0.6323", "file_id": "70", "bbox": "180 26 228 75"}, {"confidence": "0.6317", "file_id": "125", "bbox": "141 82 190 130"}, {"confidence": "0.6253", "file_id": "165", "bbox": "100 139 150 190"}, {"confidence": "0.6163", "file_id": "101", "bbox": "144 23 192 78"}, {"confidence": "0.6124", "file_id": "123", "bbox": "284 77 333 127"}, {"confidence": "0.6087", "file_id": "121", "bbox": "53 120 102 172"}, {"confidence": "0.5982", "file_id": "177", "bbox": "0 0 415 415"}, {"confidence": "0.5875", "file_id": "27", "bbox": "0 0 415 415"}, {"confidence": "0.5829", "file_id": "118", "bbox": "141 95 188 141"}, {"confidence": "0.5746", "file_id": "59", "bbox": "3 23 53 77"}, {"confidence": "0.5655", "file_id": "130", "bbox": "18 80 64 130"}, {"confidence": "0.5621", "file_id": "50", "bbox": "32 72 87 122"}, {"confidence": "0.5558", "file_id": "117", "bbox": "0 0 415 415"}, {"confidence": "0.5485", "file_id": "162", "bbox": "33 113 81 161"}, {"confidence": "0.5446", "file_id": "92", "bbox": "32 112 80 158"}, {"confidence": "0.5327", "file_id": "16", "bbox": "0 0 415 415"}, {"confidence": "0.5182", "file_id": "143", "bbox": "0 0 415 415"}, {"confidence": "0.5168", "file_id": "105", "bbox": "47 124 92 170"}, {"confidence": "0.4902", "file_id": "107", "bbox": "365 50 410 102"}, {"confidence": "0.4816", "file_id": "144", "bbox": "95 37 146 80"}, {"confidence": "0.4815", "file_id": "181", "bbox": "33 113 79 159"}, {"confidence": "0.4656", "file_id": "73", "bbox": "47 61 91 112"}, {"confidence": "0.4562", "file_id": "192", "bbox": "98 123 135 181"}, {"confidence": "0.4543", "file_id": "193", "bbox": "134 135 181 197"}, {"confidence": "0.4507", "file_id": "173", "bbox": "47 90 102 144"}, {"confidence": "0.4477", "file_id": "100", "bbox": "0 0 415 415"}, {"confidence": "0.4449", "file_id": "163", "bbox": "280 117 340 160"}, {"confidence": "0.4376", "file_id": "186", "bbox": "24 83 83 134"}, {"confidence": "0.4360", "file_id": "25", "bbox": "0 0 415 415"}, {"confidence": "0.4289", "file_id": "84", "bbox": "141 176 193 227"}, {"confidence": "0.4228", "file_id": "146", "bbox": "15 93 63 144"}, {"confidence": "0.4110", "file_id": "52", "bbox": "217 18 269 67"}, {"confidence": "0.4088", "file_id": "62", "bbox": "270 107 325 160"}, {"confidence": "0.4066", "file_id": "42", "bbox": "71 125 131 176"}, {"confidence": "0.4010", "file_id": "95", "bbox": "200 27 249 80"}, {"confidence": "0.3831", "file_id": "187", "bbox": "124 172 187 226"}, {"confidence": "0.3788", "file_id": "100", "bbox": "277 53 320 96"}, {"confidence": "0.3709", "file_id": "42", "bbox": "141 153 196 207"}, {"confidence": "0.3688", "file_id": "23", "bbox": "285 141 336 193"}, {"confidence": "0.3614", "file_id": "147", "bbox": "0 0 415 415"}, {"confidence": "0.3613", "file_id": "73", "bbox": "103 92 157 147"}, {"confidence": "0.3590", "file_id": "106", "bbox": "0 0 415 415"}, {"confidence": "0.3565", "file_id": "104", "bbox": "170 54 221 110"}, {"confidence": "0.3546", "file_id": "55", "bbox": "12 18 61 65"}, {"confidence": "0.3413", "file_id": "61", "bbox": "0 0 415 415"}, {"confidence": "0.3290", "file_id": "94", "bbox": "110 84 157 132"}, {"confidence": "0.3288", "file_id": "51", "bbox": "62 131 117 173"}, {"confidence": "0.3176", "file_id": "127", "bbox": "112 42 161 102"}, {"confidence": "0.3174", "file_id": "34", "bbox": "296 108 352 172"}, {"confidence": "0.3144", "file_id": "5", "bbox": "269 5 319 52"}, {"confidence": "0.3013", "file_id": "89", "bbox": "185 166 238 212"}]